{
  "users": [
    {
      "id": 1,
      "name": "박윤아",
      "email": "yuna@example.com",
      "password": "test"
    },
    {
      "id": 2,
      "name": "김현종",
      "email": "hyeon@example.com",
      "password": "admin"
    },
    {
      "email": 11,
      "password": 10,
      "name": 1000,
      "id": 3
    },
    {
      "email": "현종@현종.com",
      "password": "qqqq1111",
      "name": "현종",
      "id": 4
    }
  ],
  "transactions": [
    {
      "userId": 1,
      "id": 1,
      "type": "income",
      "amount": 2500000,
      "date": "2026-04-01",
      "content": "정기 급여",
      "category": "급여",
      "memo": "고생했다 나 자신!",
      "isIncluded": true
    },
    {
      "userId": 1,
      "id": 2,
      "type": "expense",
      "amount": 12500,
      "date": "2026-04-01",
      "content": "김밥천국",
      "category": "식비",
      "memo": "라돈세트",
      "isIncluded": true
    },
    {
      "userId": 1,
      "id": 3,
      "type": "expense",
      "amount": 1250,
      "date": "2026-04-02",
      "content": "지하철",
      "category": "교통",
      "memo": "출근",
      "isIncluded": true
    },
    {
      "userId": 1,
      "id": 4,
      "type": "expense",
      "amount": 8000,
      "date": "2026-04-02",
      "content": "스타벅스",
      "category": "식비",
      "memo": "돌체 라떼",
      "isIncluded": true
    },
    {
      "userId": 1,
      "id": 5,
      "type": "expense",
      "amount": 15000,
      "date": "2026-04-04",
      "content": "서점",
      "category": "문화 생활",
      "memo": "소설책 한 권",
      "isIncluded": true
    },
    {
      "userId": 1,
      "id": 6,
      "type": "expense",
      "amount": 55000,
      "date": "2026-04-04",
      "content": "쿠팡",
      "category": "쇼핑",
      "memo": "생필품 쇼핑",
      "isIncluded": true
    },
    {
      "userId": 1,
      "id": 7,
      "type": "expense",
      "amount": 2500,
      "date": "2026-04-04",
      "content": "편의점",
      "category": "식비",
      "memo": "젤리",
      "isIncluded": true
    },
    {
      "userId": 1,
      "id": 8,
      "type": "expense",
      "amount": 120000,
      "date": "2026-04-04",
      "content": "나이키",
      "category": "쇼핑",
      "memo": "운동화",
      "isIncluded": true
    },
    {
      "userId": 1,
      "id": 9,
      "type": "expense",
      "amount": 15000,
      "date": "2026-04-05",
      "content": "CGV",
      "category": "문화 생활",
      "memo": "영화 관람",
      "isIncluded": true
    },
    {
      "userId": 1,
      "id": 10,
      "type": "expense",
      "amount": 9000,
      "date": "2026-04-06",
      "content": "버거킹",
      "category": "식비",
      "memo": "통새우와퍼",
      "isIncluded": true
    },
    {
      "userId": 1,
      "id": 11,
      "type": "expense",
      "amount": 4500,
      "date": "2026-04-06",
      "content": "빽다방",
      "category": "식비",
      "memo": "아메리카노",
      "isIncluded": true
    },
    {
      "userId": 1,
      "id": 12,
      "type": "expense",
      "amount": 3200,
      "date": "2026-04-06",
      "content": "따릉이",
      "category": "교통",
      "memo": "운동 겸 퇴근",
      "isIncluded": true
    },
    {
      "userId": 1,
      "id": 13,
      "type": "income",
      "amount": 15000,
      "date": "2026-04-07",
      "content": "캐시워크",
      "category": "기타 수입",
      "memo": "포인트 환급",
      "isIncluded": true
    },
    {
      "userId": 1,
      "id": 14,
      "type": "expense",
      "amount": 12000,
      "date": "2026-04-07",
      "content": "돈까스집",
      "category": "식비",
      "memo": "점심 외식",
      "isIncluded": true
    },
    {
      "userId": 1,
      "id": 15,
      "type": "expense",
      "amount": 28000,
      "date": "2026-04-08",
      "content": "올리브영",
      "category": "쇼핑",
      "memo": "클렌징 폼",
      "isIncluded": true
    },
    {
      "userId": 1,
      "id": 16,
      "type": "expense",
      "amount": 8500,
      "date": "2026-04-08",
      "content": "서브웨이",
      "category": "식비",
      "memo": "에그마요",
      "isIncluded": true
    },
    {
      "userId": 1,
      "id": 17,
      "type": "income",
      "amount": 50000,
      "date": "2026-04-09",
      "content": "당근마켓",
      "category": "기타 수입",
      "memo": "모니터 판매",
      "isIncluded": true
    },
    {
      "userId": 1,
      "id": 18,
      "type": "expense",
      "amount": 4200,
      "date": "2026-04-09",
      "content": "GS25",
      "category": "식비",
      "memo": "간식",
      "isIncluded": true
    },
    {
      "userId": 1,
      "id": 19,
      "type": "expense",
      "amount": 150000,
      "date": "2026-04-10",
      "content": "관리비",
      "category": "고정 지출",
      "memo": "4월 관리비",
      "isIncluded": true
    },
    {
      "userId": 1,
      "id": 20,
      "type": "expense",
      "amount": 45000,
      "date": "2026-04-11",
      "content": "술집",
      "category": "식비",
      "memo": "불금!",
      "isIncluded": true
    },
    {
      "userId": 1,
      "id": 21,
      "type": "expense",
      "amount": 12000,
      "date": "2026-04-12",
      "content": "카페",
      "category": "식비",
      "memo": "카공",
      "isIncluded": true
    },
    {
      "userId": 1,
      "id": 22,
      "type": "expense",
      "amount": 3500,
      "date": "2026-04-13",
      "content": "버스",
      "category": "교통",
      "memo": "외근",
      "isIncluded": true
    },
    {
      "userId": 1,
      "id": 23,
      "type": "expense",
      "amount": 11000,
      "date": "2026-04-14",
      "content": "중국집",
      "category": "식비",
      "memo": "짜장면",
      "isIncluded": true
    },
    {
      "userId": 1,
      "id": 24,
      "type": "expense",
      "amount": 60000,
      "date": "2026-04-15",
      "content": "주유소",
      "category": "교통",
      "memo": "기름 가득",
      "isIncluded": true
    },
    {
      "userId": 1,
      "id": 25,
      "type": "expense",
      "amount": 5000,
      "date": "2026-04-16",
      "content": "다이소",
      "category": "쇼핑",
      "memo": "청소도구",
      "isIncluded": true
    },
    {
      "userId": 1,
      "id": 26,
      "type": "income",
      "amount": 30000,
      "date": "2026-04-17",
      "content": "친구 송금",
      "category": "기타 수입",
      "memo": "더치페이 정산",
      "isIncluded": true
    },
    {
      "userId": 1,
      "id": 27,
      "type": "expense",
      "amount": 25000,
      "date": "2026-04-18",
      "content": "미용실",
      "category": "기타",
      "memo": "커트",
      "isIncluded": true
    },
    {
      "userId": 1,
      "id": 28,
      "type": "expense",
      "amount": 90000,
      "date": "2026-04-19",
      "content": "백화점",
      "category": "쇼핑",
      "memo": "선물",
      "isIncluded": true
    },
    {
      "userId": 1,
      "id": 29,
      "type": "expense",
      "amount": 1500,
      "date": "2026-04-20",
      "content": "자판기",
      "category": "식비",
      "memo": "음료수",
      "isIncluded": true
    },
    {
      "userId": 1,
      "id": 30,
      "type": "expense",
      "amount": 7500,
      "date": "2026-04-21",
      "content": "분식집",
      "category": "식비",
      "memo": "떡볶이",
      "isIncluded": true
    },
    {
      "userId": 1,
      "type": "expense",
      "amount": 5900,
      "date": "2026-04-11",
      "content": "카공족 성남신흥점",
      "category": "교육",
      "memo": "집가고싶다",
      "isIncluded": true,
      "id": 31
    },
    {
      "userId": 4,
      "type": "expense",
      "date": "2026-04-11",
      "amount": 11,
      "content": "11",
      "category": "쇼핑",
      "memo": "ㅁㄴㅇ",
      "isIncluded": false,
      "id": 32
    },
    {
      "userId": 4,
      "type": "income",
      "date": "2026-04-11",
      "amount": 123123,
      "content": "12",
      "category": "기타 수입",
      "memo": "ㅇㅇ",
      "isIncluded": true,
      "id": 33
    },
    {
      "userId": 4,
      "type": "income",
      "date": "2026-04-11",
      "amount": 123123,
      "content": "2",
      "category": "급여",
      "memo": "",
      "isIncluded": true,
      "id": 34
    },
    {
      "userId": 4,
      "type": "income",
      "date": "2026-04-11",
      "amount": 12333,
      "content": "33",
      "category": "용돈",
      "memo": "",
      "isIncluded": true,
      "id": 36
    }
  ]
}